{
 "idx": 17,
 "cardnewsId": "6259153a-17ee-4ff6-9d72-c7c29afa2fed",
 "captionCn": "你知道孩子祖父母的身高吗？🧬\n\n你是否曾疑惑，为什么有些孩子比父母高很多，或者父母都高，孩子却比同龄人矮？这背后往往藏着「隔代遗传」的秘密——祖父母那一代沉睡的基因，可能在孙辈身上重新苏醒。因此，要准确评估孩子的成长潜力，了解四位祖父母的身高非常重要。\n\n孩子的可能性，也许比你想象的更大。更多信息请点选个人主页链接 🌱",
 "hashtagsCn": "#隔代遗传 #祖父母身高 #孩子身高 #身高遗传 #成长潜力 #儿童生长 #生长激素 #骨龄检查 #矮小症 #家族性矮小 #儿童健康 #187生长诊所 #身高预测 #成长门诊 #儿科医生",
 "slides": [
  {
   "slideId": "9b99dd7e-3900-4766-9e17-2cb29db757bc",
   "cn": {
    "headline": "祖父母的身高，为什么重要？",
    "subtext": ""
   }
  },
  {
   "slideId": "916bba05-1e27-4674-bd4a-483579ea5d7d",
   "cn": {
    "headline": "光看父母身高还不够的原因",
    "subtext": "遗传不只来自父母，也来自祖父母"
   }
  },
  {
   "slideId": "2a01baa6-71a1-481d-95f2-06501c3959c2",
   "cn": {
    "headline": "隔代遗传——沉睡的基因苏醒了",
    "subtext": "在父母身上沉寂的基因，可能在孩子身上重新表现"
   }
  },
  {
   "slideId": "46e8c7e4-2bb4-4a7a-b75b-cff7e4d6ba37",
   "cn": {
    "headline": "父母高，孩子不一定也高",
    "subtext": "祖父母潜藏的基因可能跨代出现在孙辈身上"
   }
  },
  {
   "slideId": "98138473-a891-48c3-b6bf-763e46414c16",
   "cn": {
    "headline": "家族史要追溯到祖父母才完整",
    "subtext": "了解四位祖父母的身高，才能更准确评估孩子的成长潜力"
   }
  },
  {
   "slideId": "d7cd869a-d861-46e0-a96e-be94c2167679",
   "cn": {
    "headline": "提升成长潜力的4个步骤",
    "subtext": "家族史调查 · 骨龄分析 · 把握时机 · 个性化策略"
   }
  },
  {
   "slideId": "d5c6ed66-8281-4147-a238-8204855da917",
   "cn": {
    "headline": "一起探索孩子隐藏的成长潜力",
    "subtext": "包含祖父母的完整家族史，能为孩子开启更多可能性"
   }
  }
 ]
}
